ikewaipy/__init__.py
ikewaipy/ikewai.py
ikewaipy-0.1.2.dist-info/LICENSE
ikewaipy-0.1.2.dist-info/WHEEL
ikewaipy-0.1.2.dist-info/METADATA
ikewaipy-0.1.2.dist-info/RECORD
